intechinvestments/__init__.py
intechinvestments/brand.py
intechinvestments-0.0.5.dist-info/METADATA
intechinvestments-0.0.5.dist-info/WHEEL
intechinvestments-0.0.5.dist-info/entry_points.txt
intechinvestments-0.0.5.dist-info/top_level.txt
intechinvestments-0.0.5.dist-info/RECORD
