Metadata-Version: 2.1
Name: intechinvestments
Version: 0.0.5
Summary: Intech Investments Branding
Home-page: https://www.intechinvestments.com/contact
Author: microprediction
Author-email: info@3za.org
License: MIT
Platform: UNKNOWN
Classifier: License :: OSI Approved :: MIT License
Classifier: Programming Language :: Python :: 3
Classifier: Programming Language :: Python :: 3.7
